virtual/conf.py
virtual/version.py
virtual/grains/virtual/init.py
virtual/grains/virtual/virtual.py
grains_virt-3.dist-info/METADATA
grains_virt-3.dist-info/WHEEL
grains_virt-3.dist-info/top_level.txt
grains_virt-3.dist-info/RECORD
