Metadata-Version: 2.1
Name: grains-virt
Version: 3
Summary: Virtualization grains for grainsv2 horizontal merging
Home-page: https://gitlab.com/saltstack/pop/corn_virtualization
Author: Tyler Johnson
Author-email: tjohnson@saltstack.com
License: UNKNOWN
Platform: UNKNOWN
Classifier: Operating System :: OS Independent
Classifier: Programming Language :: Python
Classifier: Programming Language :: Python :: 3.6
Classifier: Programming Language :: Python :: 3.7
Classifier: Programming Language :: Python :: 3.8
Classifier: Development Status :: 5 - Production/Stable
Requires-Python: >=3.6
Requires-Dist: aiofiles (>=0.3.0)
Requires-Dist: grainsv2 (>=10)
Requires-Dist: pop (>=13.3)
